README.md
setup.py
ci/__init__.py
ci/test_LinuxWatchdog.py
ci/test_Plumber.py
ci/test_Sink.py
ci/test_Task.py
pyplumber/Plumber.c
pyplumber/Plumber.py
pyplumber/Sink.c
pyplumber/Sink.py
pyplumber/Task.c
pyplumber/Task.py
pyplumber/__init__.c
pyplumber/__init__.py
pyplumber/exceptions.c
pyplumber/exceptions.py
pyplumber/log.py
pyplumber.egg-info/PKG-INFO
pyplumber.egg-info/SOURCES.txt
pyplumber.egg-info/dependency_links.txt
pyplumber.egg-info/requires.txt
pyplumber.egg-info/top_level.txt