Metadata-Version: 2.1
Name: pyplumber
Version: 0.1.4
Summary: PyPlumber provides some tools for looping pipelines using tasks and daemonized jobs.
Home-page: https://github.com/gabriel-milan/pyplumber
Author: Gabriel Gazola Milan
Author-email: gabriel.gazola@poli.ufrj.br
License: GPL-3.0
Keywords: framework,shared resources,flexibility,python,online,pipelines
Platform: UNKNOWN
Classifier: Development Status :: 4 - Beta
Classifier: Intended Audience :: Developers
Classifier: Topic :: Software Development :: Libraries :: Python Modules
Classifier: License :: OSI Approved :: GNU General Public License v3 (GPLv3)
Classifier: Programming Language :: Python :: 3
Classifier: Programming Language :: Python :: 3.7
Classifier: Programming Language :: Python :: 3.8
Classifier: Programming Language :: Python :: 3.9
Provides-Extra: test
